ansys/tools/visualization_interface/__init__.py
ansys/tools/visualization_interface/plotter.py
ansys/tools/visualization_interface/backends/__init__.py
ansys/tools/visualization_interface/backends/_base.py
ansys/tools/visualization_interface/backends/pyvista/__init__.py
ansys/tools/visualization_interface/backends/pyvista/picker.py
ansys/tools/visualization_interface/backends/pyvista/pyvista.py
ansys/tools/visualization_interface/backends/pyvista/pyvista_interface.py
ansys/tools/visualization_interface/backends/pyvista/trame_local.py
ansys/tools/visualization_interface/backends/pyvista/trame_remote.py
ansys/tools/visualization_interface/backends/pyvista/trame_service.py
ansys/tools/visualization_interface/backends/pyvista/widgets/__init__.py
ansys/tools/visualization_interface/backends/pyvista/widgets/button.py
ansys/tools/visualization_interface/backends/pyvista/widgets/dark_mode.py
ansys/tools/visualization_interface/backends/pyvista/widgets/displace_arrows.py
ansys/tools/visualization_interface/backends/pyvista/widgets/hide_buttons.py
ansys/tools/visualization_interface/backends/pyvista/widgets/measure.py
ansys/tools/visualization_interface/backends/pyvista/widgets/mesh_slider.py
ansys/tools/visualization_interface/backends/pyvista/widgets/pick_rotation_center.py
ansys/tools/visualization_interface/backends/pyvista/widgets/ruler.py
ansys/tools/visualization_interface/backends/pyvista/widgets/screenshot.py
ansys/tools/visualization_interface/backends/pyvista/widgets/view_button.py
ansys/tools/visualization_interface/backends/pyvista/widgets/widget.py
ansys/tools/visualization_interface/backends/pyvista/widgets/_images/+xy.png
ansys/tools/visualization_interface/backends/pyvista/widgets/_images/+xy_inv.png
ansys/tools/visualization_interface/backends/pyvista/widgets/_images/+xz.png
ansys/tools/visualization_interface/backends/pyvista/widgets/_images/+xz_inv.png
ansys/tools/visualization_interface/backends/pyvista/widgets/_images/+yz.png
ansys_tools_visualization_interface-0.12.1.dist-info/LICENSE
ansys_tools_visualization_interface-0.12.1.dist-info/WHEEL
ansys_tools_visualization_interface-0.12.1.dist-info/METADATA
ansys_tools_visualization_interface-0.12.1.dist-info/RECORD
