Metadata-Version: 2.3
Name: ansys-tools-visualization-interface
Version: 0.12.1
Summary: A Python visualization interface for PyAnsys libraries
Author-email: "ANSYS, Inc." <pyansys.core@ansys.com>
Maintainer-email: "ANSYS, Inc." <pyansys.core@ansys.com>
Requires-Python: >=3.10,<4
Classifier: Development Status :: 4 - Beta
Classifier: Intended Audience :: Science/Research
Classifier: Topic :: Scientific/Engineering :: Information Analysis
Classifier: License :: OSI Approved :: MIT License
Classifier: Operating System :: OS Independent
Classifier: Programming Language :: Python :: 3.10
Classifier: Programming Language :: Python :: 3.11
Classifier: Programming Language :: Python :: 3.12
Classifier: Programming Language :: Python :: 3.13
Requires-Dist: pyvista >= 0.43.0,<1
Requires-Dist: websockets >= 12.0,< 16
Requires-Dist: trame >= 3.6.0,<4
Requires-Dist: trame-vtk >= 2.8.7,<3,!=2.8.16
Requires-Dist: trame-vuetify >= 2.4.3,< 4
Requires-Dist: trame-router >= 2.3.0,<3
Requires-Dist: pyvista==0.46.3 ; extra == "doc"
Requires-Dist: ansys-sphinx-theme[autoapi]==1.6.1 ; extra == "doc"
Requires-Dist: jupyter_sphinx==0.5.3 ; extra == "doc"
Requires-Dist: jupytext==1.17.3 ; extra == "doc"
Requires-Dist: nbsphinx==0.9.6 ; extra == "doc"
Requires-Dist: numpydoc==1.9.0 ; extra == "doc"
Requires-Dist: sphinx==8.2.3 ; extra == "doc"
Requires-Dist: sphinx-copybutton==0.5.2 ; extra == "doc"
Requires-Dist: sphinx_design==0.6.1 ; extra == "doc"
Requires-Dist: sphinx-gallery==0.19.0 ; extra == "doc"
Requires-Dist: sphinx-jinja==2.0.2 ; extra == "doc"
Requires-Dist: ansys-fluent-core==0.35.0 ; extra == "doc"
Requires-Dist: pyside6 >= 6.8.0,<7 ; extra == "pyvistaqt"
Requires-Dist: pyvistaqt >= 0.11.1,<1 ; extra == "pyvistaqt"
Requires-Dist: pytest==8.4.2 ; extra == "tests"
Requires-Dist: pyvista==0.46.3 ; extra == "tests"
Requires-Dist: pytest-pyvista==0.2.0 ; extra == "tests"
Requires-Dist: pytest-cov==7.0.0 ; extra == "tests"
Requires-Dist: pyside6==6.9.3 ; extra == "tests"
Project-URL: Discussions, https://github.com/ansys/ansys-tools-visualization-interface/discussions
Project-URL: Documentation, https://visualization-interface.tools.docs.pyansys.com/
Project-URL: Issues, https://github.com/ansys/ansys-tools-visualization-interface/issues
Project-URL: Releases, https://github.com/ansys/ansys-tools-visualization-interface/releases/
Project-URL: Source, https://github.com/ansys/ansys-tools-visualization-interface
Provides-Extra: doc
Provides-Extra: pyvistaqt
Provides-Extra: tests
